charm_refresh/__init__.py
charm_refresh/_main.py
charm_refresh-3.1.1.2.dist-info/METADATA
charm_refresh-3.1.1.2.dist-info/WHEEL
charm_refresh-3.1.1.2.dist-info/RECORD
